MANIFEST.in
README.md
setup.py
nanoplotter/__init__.py
nanoplotter/nanoplotter_main.py
nanoplotter/plot.py
nanoplotter/spatial_heatmap.py
nanoplotter/timeplots.py
nanoplotter/version.py
nanoplotter.egg-info/PKG-INFO
nanoplotter.egg-info/SOURCES.txt
nanoplotter.egg-info/dependency_links.txt
nanoplotter.egg-info/requires.txt
nanoplotter.egg-info/top_level.txt
scripts/test.sh